src/__init__.py
src/hierarchical_context.py
src/hierarchical_model.py
src/utils/__init__.py
src/utils/data_utils.py
src/utils/matric.py
src/utils/model_utils.py
src/utils/result_utils.py
src/utils/visualize.py
StructureContext-0.1.0.dist-info/METADATA
StructureContext-0.1.0.dist-info/WHEEL
StructureContext-0.1.0.dist-info/top_level.txt
StructureContext-0.1.0.dist-info/RECORD
