Metadata-Version: 2.2
Name: StructureContext
Version: 0.1.0
Summary: structre context for code project
Home-page: https://github.com/qikahh/StructuredContext
Author: qikahhh
Author-email: 2101213934@stu.pku.edu.cn
Classifier: Programming Language :: Python :: 3
Classifier: License :: OSI Approved :: MIT License
Classifier: Operating System :: OS Independent
Requires-Python: >=3.9
Requires-Dist: accelerate==0.26.1
Requires-Dist: annotated-types==0.6.0
Requires-Dist: anyio==4.3.0
Requires-Dist: async-timeout==4.0.3
Requires-Dist: bcrypt==4.2.0
Requires-Dist: blobfile==3.0.0
Requires-Dist: cachetools==5.3.2
Requires-Dist: click==8.1.7
Requires-Dist: cloudpickle==3.0.0
Requires-Dist: cmake==3.29.3
Requires-Dist: colander==2.0
Requires-Dist: colorama==0.4.6
Requires-Dist: contourpy==1.3.1
Requires-Dist: cornice==6.1.0
Requires-Dist: cornice-swagger==1.0.1
Requires-Dist: cycler==0.12.1
Requires-Dist: diskcache==5.6.3
Requires-Dist: distro==1.9.0
Requires-Dist: dockerflow==2024.4.2
Requires-Dist: editdistance==0.6.2
Requires-Dist: elementpath==4.1.5
Requires-Dist: email-validator==2.1.1
Requires-Dist: fastapi==0.93.0
Requires-Dist: fastapi-cli==0.0.3
Requires-Dist: fonttools==4.55.8
Requires-Dist: fsspec==2023.12.2
Requires-Dist: fuzzywuzzy==0.18.0
Requires-Dist: h11==0.14.0
Requires-Dist: httpcore==1.0.5
Requires-Dist: httptools==0.6.1
Requires-Dist: httpx==0.27.0
Requires-Dist: huggingface-hub==0.26.3
Requires-Dist: hupper==1.12.1
Requires-Dist: interegular==0.3.3
Requires-Dist: iso8601==2.1.0
Requires-Dist: jieba==0.42.1
Requires-Dist: jinja2==3.1.3
Requires-Dist: joblib==1.3.2
Requires-Dist: jsonlines==4.0.0
Requires-Dist: jsonschema==4.22.0
Requires-Dist: jsonschema-specifications==2023.12.1
Requires-Dist: kinto==18.1.1
Requires-Dist: kinto-redis==2.1.0
Requires-Dist: kiwisolver==1.4.8
Requires-Dist: lark==1.1.9
Requires-Dist: llvmlite==0.42.0
Requires-Dist: lm-format-enforcer==0.9.8
Requires-Dist: logging-color-formatter==1.1.0
Requires-Dist: lxml==5.3.0
Requires-Dist: markdown-it-py==3.0.0
Requires-Dist: matplotlib==3.10.0
Requires-Dist: mdurl==0.1.2
Requires-Dist: memory-profiler==0.61.0
Requires-Dist: modelscope==1.20.1
Requires-Dist: msgpack==1.0.8
Requires-Dist: ninja==1.11.1.1
Requires-Dist: nltk==3.8.1
Requires-Dist: numba==0.59.1
Requires-Dist: numpy==1.26.2
Requires-Dist: nvidia-cublas-cu12==12.1.3.1
Requires-Dist: nvidia-cuda-cupti-cu12==12.1.105
Requires-Dist: nvidia-cuda-nvrtc-cu12==12.1.105
Requires-Dist: nvidia-cuda-runtime-cu12==12.1.105
Requires-Dist: nvidia-cudnn-cu12==8.9.2.26
Requires-Dist: nvidia-cufft-cu12==11.0.2.54
Requires-Dist: nvidia-curand-cu12==10.3.2.106
Requires-Dist: nvidia-cusolver-cu12==11.4.5.107
Requires-Dist: nvidia-cusparse-cu12==12.1.0.106
Requires-Dist: nvidia-ml-py==12.535.133
Requires-Dist: nvidia-nccl-cu12==2.20.5
Requires-Dist: nvidia-nvjitlink-cu12==12.4.127
Requires-Dist: nvidia-nvtx-cu12==12.1.105
Requires-Dist: nvitop==1.3.2
Requires-Dist: openai==1.30.1
Requires-Dist: orjson==3.10.3
Requires-Dist: outlines==0.0.34
Requires-Dist: pandas==2.1.2
Requires-Dist: pastedeploy==3.1.0
Requires-Dist: pillow==10.1.0
Requires-Dist: plaster==1.1.2
Requires-Dist: plaster-pastedeploy==1.0.1
Requires-Dist: prometheus-client==0.20.0
Requires-Dist: prometheus-fastapi-instrumentator==7.0.0
Requires-Dist: protobuf==5.26.1
Requires-Dist: psutil==5.9.7
Requires-Dist: py-cpuinfo==9.0.0
Requires-Dist: pyarrow==14.0.0
Requires-Dist: pycryptodomex==3.20.0
Requires-Dist: pydantic
Requires-Dist: pydantic-core
Requires-Dist: pygments==2.18.0
Requires-Dist: pyparsing==3.2.1
Requires-Dist: pyramid==2.0.2
Requires-Dist: pyramid-mailer==0.15.1
Requires-Dist: pyramid-multiauth==1.0.2
Requires-Dist: pyramid-tm==2.5
Requires-Dist: python-dotenv==1.0.1
Requires-Dist: python-multipart==0.0.9
Requires-Dist: python-rapidjson==1.20
Requires-Dist: pytz==2023.3.post1
Requires-Dist: rank-bm25==0.2.2
Requires-Dist: ray==2.22.0
Requires-Dist: redis==5.0.1
Requires-Dist: referencing==0.35.1
Requires-Dist: regex==2023.12.25
Requires-Dist: repoze-sendmail==4.4.1
Requires-Dist: rich==13.7.1
Requires-Dist: rouge==1.0.1
Requires-Dist: rpds-py==0.18.1
Requires-Dist: safetensors==0.4.1
Requires-Dist: scikit-learn==1.3.2
Requires-Dist: scipy==1.11.3
Requires-Dist: sentencepiece==0.2.0
Requires-Dist: shellingham==1.5.4
Requires-Dist: sniffio==1.3.1
Requires-Dist: starlette==0.25.0
Requires-Dist: termcolor==2.4.0
Requires-Dist: threadpoolctl==3.2.0
Requires-Dist: tiktoken==0.1.2
Requires-Dist: tokenizers==0.20.3
Requires-Dist: torch==2.3.0
Requires-Dist: torchvision==0.18.0
Requires-Dist: transaction==4.0
Requires-Dist: transformers==4.46.3
Requires-Dist: translationstring==1.4
Requires-Dist: tree-sitter==0.24.0
Requires-Dist: tree-sitter-python==0.23.6
Requires-Dist: triton==2.3.0
Requires-Dist: typer==0.12.3
Requires-Dist: ujson==5.10.0
Requires-Dist: uvicorn==0.29.0
Requires-Dist: uvloop==0.19.0
Requires-Dist: venusian==3.1.0
Requires-Dist: vllm==0.4.2
Requires-Dist: vllm-nccl-cu12==2.18.1.0.4.0
Requires-Dist: waitress==3.0.0
Requires-Dist: watchfiles==0.21.0
Requires-Dist: webob==1.8.8
Requires-Dist: websockets==12.0
Requires-Dist: wordninja==2.0.0
Requires-Dist: xformers==0.0.26.post1
Requires-Dist: xmlschema==2.5.1
Requires-Dist: yappi==1.6.10
Requires-Dist: zope-deprecation==5.0
Requires-Dist: zope-interface==7.0.3
Dynamic: author
Dynamic: author-email
Dynamic: classifier
Dynamic: description
Dynamic: description-content-type
Dynamic: home-page
Dynamic: requires-dist
Dynamic: requires-python
Dynamic: summary
